cpkg/__init__.py
cpkg/__main__.py
cpkg/cmod.py
cpkg/cpkg.py
cpkg/createPkg.py
cpkg/test.py
cpkg-0.4.21.dist-info/LICENSE
cpkg-0.4.21.dist-info/METADATA
cpkg-0.4.21.dist-info/WHEEL
cpkg-0.4.21.dist-info/entry_points.txt
cpkg-0.4.21.dist-info/top_level.txt
cpkg-0.4.21.dist-info/RECORD
