Metadata-Version: 2.1
Name: cpkg
Version: 0.4.21
Summary: A package that creates a package
Home-page: https://github.com/seoul2k/cPkg
Author: xiongtianshuo
Author-email: Mr_Xiongts@163.com
License: UNKNOWN
Project-URL: Bug Tracker, https://github.com/seoul2k/cPkg/issues
Platform: any
Classifier: Programming Language :: Python :: 3
Classifier: Programming Language :: Python :: 3.3
Classifier: Programming Language :: Python :: 3.4
Classifier: Programming Language :: Python :: 3.5
Classifier: License :: OSI Approved :: MIT License
Classifier: Operating System :: OS Independent
Classifier: Development Status :: 3 - Alpha
Requires-Python: >=3
License-File: LICENSE
